setup.py
affiliate_deeplink/__init__.py
affiliate_deeplink/afilio.py
affiliate_deeplink/amazon.py
affiliate_deeplink/awin.py
affiliate_deeplink/b2w.py
affiliate_deeplink/banggood.py
affiliate_deeplink/base.py
affiliate_deeplink/config.py
affiliate_deeplink/hurb.py
affiliate_deeplink/lomadee.py
affiliate_deeplink/magazine_luiza.py
affiliate_deeplink/natura.py
affiliate_deeplink/utils.py
affiliate_deeplink/zanox.py
affiliate_deeplink.egg-info/PKG-INFO
affiliate_deeplink.egg-info/SOURCES.txt
affiliate_deeplink.egg-info/dependency_links.txt
affiliate_deeplink.egg-info/requires.txt
affiliate_deeplink.egg-info/top_level.txt