Metadata-Version: 1.0
Name: affiliate-deeplink
Version: 0.2.0
Summary: Deeplink generator for affiliate marketing.
Home-page: https://github.com/marcelomaia/AffiliateDeeplink
Author: Marcelo Maia
Author-email: mmaia.cc@gmail.com
License: MIT
Platform: UNKNOWN
